{
 "reverse_geocoded_address_components": {
  "postal_code": "40209",
  "country_code": "US",
  "street_number": "700",
  "locality": "Louisville",
  "sublocality_1": null,
  "route": "Phillips Ln",
  "sublocality_2": null,
  "administrative_area_2": "Jefferson County",
  "administrative_area_3": null,
  "sublocality_3": null,
  "administrative_area_1": "KY"
 },
 "opening_date": "None",
 "nissan_nctc": false,
 "payment_enabled": null,
 "reverse_geocoded_address": "700 Phillips Ln, Louisville, KY 40209, USA",
 "amenities": [
  {
   "location_id": 155317,
   "type": 1
  },
  {
   "location_id": 155317,
   "type": 2
  },
  {
   "location_id": 155317,
   "type": 4
  },
  {
   "location_id": 155317,
   "type": 3
  }
 ],
 "latitude": 38.190264,
 "open247": false,
 "valid_outlets": [
  {
   "connector": 13,
   "power": 0
  },
  {
   "connector": 3,
   "power": 0
  },
  {
   "connector": 2,
   "power": 0
  },
  {
   "connector": 6,
   "power": 0
  },
  {
   "connector": 4,
   "power": 0
  },
  {
   "connector": 5,
   "power": 0
  },
  {
   "connector": 1,
   "power": 0
  }
 ],
 "phone": "",
 "e164_phone_number": "",
 "total_photos": 2,
 "locked": false,
 "title_description": "Residence Inn - Free Electric Car Charging - 6 Check-ins 2 Photos - 700 Phillips Ln, Louisville, KY 40209, USA - US - Hotel/Lodging - PlugShare",
 "name": "Residence Inn",
 "icon_type": "G",
 "enabled": true,
 "longitude": -85.74426,
 "reviews": [
  {
   "comment": "Located on the backside of the building, just follow the loop to the back. ",
   "rating": 1,
   "volts": null,
   "station_id": 316162,
   "finished": "2019-08-15T21:09:09Z",
   "user": {
    "last_name": "",
    "hide_address": false,
    "charger_type": 0,
    "country_code": "US",
    "language_code": "en-US",
    "allow_promo_email": false,
    "id": 548606,
    "notify_nearby": 0,
    "first_name": "amfhb",
    "last_login": "2019-08-27T14:41:34Z",
    "allow_notifications": null,
    "vehicle_description": "",
    "phone": "",
    "e164_phone_number": "",
    "hide_phone": false,
    "vehicle_type": 20,
    "about": "",
    "notify_nearby_radius": 0,
    "receive_grid_alerts": 0,
    "created_at": "2019-06-03T21:38:14Z",
    "photos": [
     {
      "user_id": 548606,
      "url": "https://s3.amazonaws.com/plugshare.production.photos/photos/430803.jpg",
      "created_at": "2019-06-13T18:14:30Z",
      "thumbnail": "https://s3.amazonaws.com/plugshare.production.photos/thumb/430803.png",
      "caption": "",
      "thumbnail2x": "https://s3.amazonaws.com/plugshare.production.photos/thumb2x/430803.png",
      "order": 0,
      "id": 430803
     }
    ],
    "formatted_phone_number": ""
   },
   "vehicle_name": "Fiat 500e",
   "vehicle_type": 20,
   "id": 1910767,
   "kilowatts": null,
   "created_at": "2019-08-15T20:09:09Z",
   "connector_type": 2,
   "waiting": false,
   "amps": null,
   "vehicle_default_img": "https://s3.amazonaws.com/plugshare.production.assets/vehicles/9806_cc0640_032_PWH.png"
  },
  {
   "comment": "The breaker shuts off and management has to reset it when they are available. ",
   "rating": 1,
   "volts": null,
   "station_id": 316162,
   "finished": "2019-04-20T14:40:07Z",
   "user": {
    "last_name": "",
    "hide_address": false,
    "charger_type": 0,
    "country_code": "US",
    "language_code": "en-US",
    "allow_promo_email": false,
    "id": 424088,
    "notify_nearby": 1,
    "first_name": "elektra",
    "last_login": "2019-08-17T16:11:53Z",
    "allow_notifications": null,
    "vehicle_description": "",
    "phone": "",
    "e164_phone_number": "",
    "hide_phone": false,
    "vehicle_type": 74,
    "about": "",
    "notify_nearby_radius": 10000,
    "receive_grid_alerts": 0,
    "created_at": "2018-11-11T15:28:09Z",
    "photos": [
     {
      "user_id": 424088,
      "url": "https://s3.amazonaws.com/plugshare.production.photos/photos/360241.jpg",
      "created_at": "2018-11-17T02:38:44Z",
      "thumbnail": "https://s3.amazonaws.com/plugshare.production.photos/thumb/360241.png",
      "caption": "",
      "thumbnail2x": "https://s3.amazonaws.com/plugshare.production.photos/thumb2x/360241.png",
      "order": 0,
      "id": 360241
     },
     {
      "user_id": 424088,
      "url": "https://s3.amazonaws.com/plugshare.production.photos/photos/360240.jpg",
      "created_at": "2018-11-17T02:38:06Z",
      "thumbnail": "https://s3.amazonaws.com/plugshare.production.photos/thumb/360240.png",
      "caption": "",
      "thumbnail2x": "https://s3.amazonaws.com/plugshare.production.photos/thumb2x/360240.png",
      "order": 0,
      "id": 360240
     }
    ],
    "formatted_phone_number": ""
   },
   "vehicle_name": "Honda Clarity Plug-In Hybrid",
   "vehicle_type": 74,
   "id": 1654885,
   "kilowatts": null,
   "created_at": "2019-04-20T13:40:07Z",
   "connector_type": 2,
   "waiting": false,
   "amps": null,
   "vehicle_default_img": "https://s3.amazonaws.com/plugshare.production.assets/vehicles/12454_cc0640_032_EVOX01.png"
  },
  {
   "comment": "Working great.",
   "rating": 1,
   "volts": null,
   "station_id": 316162,
   "finished": "2019-04-19T20:35:41Z",
   "user": {
    "last_name": "",
    "hide_address": false,
    "charger_type": 0,
    "country_code": "US",
    "language_code": "en-US",
    "allow_promo_email": false,
    "id": 424088,
    "notify_nearby": 1,
    "first_name": "elektra",
    "last_login": "2019-08-17T16:11:53Z",
    "allow_notifications": null,
    "vehicle_description": "",
    "phone": "",
    "e164_phone_number": "",
    "hide_phone": false,
    "vehicle_type": 74,
    "about": "",
    "notify_nearby_radius": 10000,
    "receive_grid_alerts": 0,
    "created_at": "2018-11-11T15:28:09Z",
    "photos": [
     {
      "user_id": 424088,
      "url": "https://s3.amazonaws.com/plugshare.production.photos/photos/360241.jpg",
      "created_at": "2018-11-17T02:38:44Z",
      "thumbnail": "https://s3.amazonaws.com/plugshare.production.photos/thumb/360241.png",
      "caption": "",
      "thumbnail2x": "https://s3.amazonaws.com/plugshare.production.photos/thumb2x/360241.png",
      "order": 0,
      "id": 360241
     },
     {
      "user_id": 424088,
      "url": "https://s3.amazonaws.com/plugshare.production.photos/photos/360240.jpg",
      "created_at": "2018-11-17T02:38:06Z",
      "thumbnail": "https://s3.amazonaws.com/plugshare.production.photos/thumb/360240.png",
      "caption": "",
      "thumbnail2x": "https://s3.amazonaws.com/plugshare.production.photos/thumb2x/360240.png",
      "order": 0,
      "id": 360240
     }
    ],
    "formatted_phone_number": ""
   },
   "vehicle_name": "Honda Clarity Plug-In Hybrid",
   "vehicle_type": 74,
   "id": 1653455,
   "kilowatts": null,
   "created_at": "2019-04-19T19:35:41Z",
   "connector_type": 2,
   "waiting": false,
   "amps": null,
   "vehicle_default_img": "https://s3.amazonaws.com/plugshare.production.assets/vehicles/12454_cc0640_032_EVOX01.png"
  },
  {
   "comment": "",
   "rating": 1,
   "volts": null,
   "station_id": 316162,
   "finished": "2019-01-04T21:49:09Z",
   "user": {
    "last_name": "",
    "hide_address": false,
    "charger_type": 0,
    "country_code": "US",
    "language_code": "en-US",
    "allow_promo_email": false,
    "id": 391819,
    "notify_nearby": 0,
    "first_name": "Ralph",
    "last_login": "2019-08-04T00:15:03Z",
    "allow_notifications": null,
    "vehicle_description": "",
    "phone": "",
    "e164_phone_number": "",
    "hide_phone": false,
    "vehicle_type": 74,
    "about": "",
    "notify_nearby_radius": 0,
    "receive_grid_alerts": 0,
    "created_at": "2018-08-29T14:50:40Z",
    "photos": [],
    "formatted_phone_number": ""
   },
   "vehicle_name": "Honda Clarity Plug-In Hybrid",
   "vehicle_type": 74,
   "id": 1481372,
   "kilowatts": null,
   "created_at": "2019-01-04T20:49:09Z",
   "connector_type": 2,
   "waiting": false,
   "amps": null,
   "vehicle_default_img": "https://s3.amazonaws.com/plugshare.production.assets/vehicles/12454_cc0640_032_EVOX01.png"
  },
  {
   "comment": "Worked fine",
   "rating": 1,
   "volts": null,
   "user": {
    "last_name": "",
    "hide_address": false,
    "charger_type": 0,
    "country_code": "US",
    "language_code": "en-US",
    "allow_promo_email": true,
    "id": 406038,
    "notify_nearby": 0,
    "first_name": "IMiev",
    "last_login": "2018-10-08T02:08:38Z",
    "allow_notifications": null,
    "vehicle_description": "",
    "phone": "",
    "e164_phone_number": "",
    "hide_phone": false,
    "vehicle_type": 5,
    "about": "",
    "notify_nearby_radius": 0,
    "receive_grid_alerts": 0,
    "created_at": "2018-10-06T14:25:56Z",
    "photos": [],
    "formatted_phone_number": ""
   },
   "vehicle_name": "Mitsubishi i-MiEV",
   "vehicle_type": 5,
   "id": 1343648,
   "kilowatts": null,
   "created_at": "2018-10-07T12:50:22Z",
   "connector_type": 2,
   "waiting": false,
   "amps": null,
   "vehicle_default_img": "https://s3.amazonaws.com/plugshare.production.assets/vehicles/8057_cc0640_032_A31.png"
  },
  {
   "comment": "",
   "rating": 1,
   "volts": 213,
   "finished": "2018-07-04T03:27:35Z",
   "user": {
    "last_name": "",
    "hide_address": false,
    "charger_type": 0,
    "country_code": "US",
    "language_code": "en-US",
    "allow_promo_email": false,
    "id": 357806,
    "notify_nearby": 0,
    "first_name": "Morningside",
    "last_login": "2018-08-24T20:17:35Z",
    "allow_notifications": null,
    "vehicle_description": "",
    "phone": "",
    "e164_phone_number": "",
    "hide_phone": false,
    "vehicle_type": 75,
    "about": "",
    "notify_nearby_radius": 0,
    "receive_grid_alerts": 0,
    "created_at": "2018-06-10T02:59:47Z",
    "photos": [],
    "formatted_phone_number": ""
   },
   "vehicle_name": "Tesla Model 3",
   "vehicle_type": 75,
   "id": 1196717,
   "kilowatts": 8,
   "created_at": "2018-07-04T02:27:35Z",
   "connector_type": 6,
   "waiting": false,
   "amps": 40,
   "vehicle_default_img": "https://s3.amazonaws.com/plugshare.production.assets/vehicles/12659_cc0640_032_PPSW.png"
  }
 ],
 "under_repair": false,
 "poi_name": "Hotel/Lodging",
 "locale": "US",
 "updated_at": "2019-08-15T20:09:09Z",
 "cost": false,
 "pwps_version": null,
 "id": 155317,
 "datasources": [],
 "cost_description": "",
 "access": 1,
 "score": 9,
 "description": "",
 "custom_ports": "",
 "confidence": 2,
 "hours": "",
 "all_promos": [],
 "address": "700 Phillips Ln, Louisville, KY 40209, USA",
 "parking_type_name": "Free",
 "icon": "https://s3.amazonaws.com/plugshare.production.assets/icons/G.png",
 "stations": [
  {
   "volts": null,
   "network_ext_id": null,
   "qr_enabled": null,
   "cost": 0,
   "pwps_version": null,
   "location_id": 155317,
   "id": 316162,
   "cost_description": "Unknown",
   "pre_charge_instructions": null,
   "nissan_nctc": false,
   "payment_enabled": null,
   "available": 0,
   "outlets": [
    {
     "available": null,
     "description": null,
     "power": 0,
     "volts": null,
     "kilowatts": null,
     "id": 594529,
     "connector": 2,
     "connector_type": 2,
     "amps": null,
     "available_changed_at": null,
     "outlet_index": null
    },
    {
     "available": null,
     "description": null,
     "power": 0,
     "volts": null,
     "kilowatts": null,
     "id": 594530,
     "connector": 2,
     "connector_type": 2,
     "amps": null,
     "available_changed_at": null,
     "outlet_index": null
    }
   ],
   "hours": "",
   "promos": [],
   "ocpp_version": null,
   "kilowatts": null,
   "requiresAccessCard": false,
   "manufacturer": "",
   "name": null,
   "network_id": null,
   "created_at": "2018-07-14T11:04:38Z",
   "amps": null,
   "model": "",
   "available_changed_at": null
  },
  {
   "volts": null,
   "network_ext_id": "43426_0",
   "qr_enabled": null,
   "cost": 0,
   "pwps_version": null,
   "location_id": 155317,
   "id": 299761,
   "cost_description": "Unknown",
   "pre_charge_instructions": null,
   "nissan_nctc": false,
   "network": {
    "description": "Tesla destination chargers",
    "formatted_phone_number": "+1 877-798-3752",
    "url": "http://www.teslamotors.com/destination-charging",
    "phone": "8777983752",
    "e164_phone_number": "+18777983752",
    "id": 35,
    "name": "Tesla Destination"
   },
   "payment_enabled": null,
   "available": 0,
   "outlets": [
    {
     "available": null,
     "description": null,
     "power": 0,
     "volts": null,
     "kilowatts": 8,
     "id": 572061,
     "connector": 6,
     "connector_type": 6,
     "amps": null,
     "available_changed_at": null,
     "outlet_index": null
    }
   ],
   "hours": "",
   "promos": [],
   "ocpp_version": null,
   "kilowatts": 8,
   "requiresAccessCard": false,
   "manufacturer": "Tesla",
   "name": "Residence Inn by Marriott Louisville Airport",
   "network_id": 35,
   "created_at": "2018-05-30T21:58:41Z",
   "amps": null,
   "model": "",
   "available_changed_at": null
  },
  {
   "volts": null,
   "network_ext_id": "43426_1",
   "qr_enabled": null,
   "cost": 0,
   "pwps_version": null,
   "location_id": 155317,
   "id": 299762,
   "cost_description": "Unknown",
   "pre_charge_instructions": null,
   "nissan_nctc": false,
   "network": {
    "description": "Tesla destination chargers",
    "formatted_phone_number": "+1 877-798-3752",
    "url": "http://www.teslamotors.com/destination-charging",
    "phone": "8777983752",
    "e164_phone_number": "+18777983752",
    "id": 35,
    "name": "Tesla Destination"
   },
   "payment_enabled": null,
   "available": 0,
   "outlets": [
    {
     "available": null,
     "description": null,
     "power": 0,
     "volts": null,
     "kilowatts": 8,
     "id": 572062,
     "connector": 6,
     "connector_type": 6,
     "amps": null,
     "available_changed_at": null,
     "outlet_index": null
    }
   ],
   "hours": "",
   "promos": [],
   "ocpp_version": null,
   "kilowatts": 8,
   "requiresAccessCard": false,
   "manufacturer": "Tesla",
   "name": "Residence Inn by Marriott Louisville Airport",
   "network_id": 35,
   "created_at": "2018-05-30T21:58:56Z",
   "amps": null,
   "model": "",
   "available_changed_at": null
  }
 ],
 "url": "https://www.plugshare.com/location/155317",
 "created_at": "2018-05-30T21:58:41Z",
 "promos": [],
 "photos": [
  {
   "user_id": 102440,
   "url": "https://s3.amazonaws.com/plugshare.production.photos/photos/315621.jpg",
   "created_at": "2018-07-14T11:09:17Z",
   "thumbnail": "https://s3.amazonaws.com/plugshare.production.photos/thumb/315621.png",
   "caption": "Far right side of the property by bushes.",
   "thumbnail2x": "https://s3.amazonaws.com/plugshare.production.photos/thumb2x/315621.png",
   "order": 0,
   "id": 315621
  },
  {
   "user_id": 357806,
   "url": "https://s3.amazonaws.com/plugshare.production.photos/photos/311683.jpg",
   "created_at": "2018-07-04T02:29:20Z",
   "thumbnail": "https://s3.amazonaws.com/plugshare.production.photos/thumb/311683.png",
   "caption": "",
   "thumbnail2x": "https://s3.amazonaws.com/plugshare.production.photos/thumb2x/311683.png",
   "order": 0,
   "id": 311683
  }
 ],
 "formatted_phone_number": "",
 "coming_soon": null,
 "total_reviews": 6
}